asset.cpython-312-x86_64-linux-gnu.so
asset_asrl.libs/libiomp5-9c6d353b.so
asset_asrl-0.5.1.data/data/asset_asrl/intel-issl.pdf
asset_asrl-0.5.1.data/data/asset_asrl/keplerprop.txt
asset_asrl-0.5.1.data/data/asset_asrl/pybind11-bsd.txt
asset_asrl-0.5.1.data/data/asset_asrl/lambert.txt
asset_asrl-0.5.1.data/data/asset_asrl/eigen-mpl2.txt
asset_asrl-0.5.1.data/data/asset_asrl/fmt-mit.txt
asset_asrl-0.5.1.data/data/asset_asrl/asset-apache2.txt
asset_asrl/__init__.py
asset_asrl/Extensions/__init__.py
asset_asrl/test/__init__.py
asset_asrl/test/test_VectorFunctions/__init__.py
asset_asrl/test/test_VectorFunctions/test_Tables.py
asset_asrl/test/test_AutoScaling/__init__.py
asset_asrl/test/test_AutoScaling/test_Reentry.py
asset_asrl/test/test_AutoScaling/test_ObjScaling.py
asset_asrl/test/test_AdaptiveMesh/test_CartPole.py
asset_asrl/test/test_AdaptiveMesh/__init__.py
asset_asrl/test/test_AdaptiveMesh/test_Delta3Launch.py
asset_asrl/test/test_AdaptiveMesh/test_Reentry.py
asset_asrl/test/test_FullProblems/test_FreeFlyingRobot.py
asset_asrl/test/test_FullProblems/test_CartPole.py
asset_asrl/test/test_FullProblems/__init__.py
asset_asrl/test/test_FullProblems/test_RosenBrock.py
asset_asrl/test/test_FullProblems/test_Delta3Launch.py
asset_asrl/test/test_FullProblems/test_MultiPhaseCannon.py
asset_asrl/test/test_FullProblems/test_Reentry.py
asset_asrl/test/test_OptimalControl/__init__.py
asset_asrl/test/test_OptimalControl/test_Integrators.py
asset_asrl/OptimalControl/__init__.py
asset_asrl/OptimalControl/MeshErrorPlots.py
asset_asrl/OptimalControl/ODEBaseClass.py
asset_asrl/OptimalControl/Extensions/__init__.py
asset_asrl/VectorFunctions/__init__.py
asset_asrl/VectorFunctions/Extensions/__init__.py
asset_asrl/VectorFunctions/Extensions/DerivChecker.py
asset_asrl/Utils/__init__.py
asset_asrl/Utils/Extensions/__init__.py
asset_asrl/Solvers/__init__.py
asset_asrl/Solvers/Extensions/__init__.py
asset_asrl/Astro/DataReadWrite.py
asset_asrl-0.5.1.dist-info/top_level.txt
asset_asrl-0.5.1.dist-info/RECORD
asset_asrl-0.5.1.dist-info/METADATA
asset_asrl-0.5.1.dist-info/WHEEL
